django_carpet/__init__.py
django_carpet/choices.py
django_carpet/env.py
django_carpet/exceptions.py
django_carpet/mixins.py
django_carpet/paginate.py
django_carpet/response.py
django_carpet/validators.py
django_carpet/xml_element.py
django_carpet-0.4.5.dist-info/licenses/LICENSE
test/__init__.py
test/dummy_django_settings.py
test/test_response.py
test/test_validators.py
test/test_xml_element.py
django_carpet-0.4.5.dist-info/METADATA
django_carpet-0.4.5.dist-info/WHEEL
django_carpet-0.4.5.dist-info/top_level.txt
django_carpet-0.4.5.dist-info/RECORD
