Metadata-Version: 2.4
Name: django_carpet
Version: 0.4.5
Summary: Foundational functionalities for Django
Home-page: https://github.com/Vieolo/django-carpet.git
Author: Vieolo
Classifier: Programming Language :: Python :: 3
Classifier: License :: OSI Approved :: MIT License
Classifier: Operating System :: OS Independent
Requires-Python: >=3.11
License-File: LICENSE
Dynamic: author
Dynamic: classifier
Dynamic: description
Dynamic: description-content-type
Dynamic: home-page
Dynamic: license-file
Dynamic: requires-python
Dynamic: summary
